fleksychallenge/__init__.py
fleksychallenge/cli.py
fleksychallenge/config.cfg
fleksychallenge/interact.py
fleksychallenge/prepare.py
fleksychallenge/test.py
fleksychallenge/train.py
fleksychallenge-1.0.0.dist-info/LICENSE
fleksychallenge-1.0.0.dist-info/METADATA
fleksychallenge-1.0.0.dist-info/WHEEL
fleksychallenge-1.0.0.dist-info/entry_points.txt
fleksychallenge-1.0.0.dist-info/top_level.txt
fleksychallenge-1.0.0.dist-info/RECORD
