Metadata-Version: 2.1
Name: fleksychallenge
Version: 1.0.0
Summary: Part 1 of the Fleksy NLP challenge
Home-page: https://github.com/astariul/fleksychallenge
Author: Nicolas REMOND
Author-email: remondnicola@gmail.com
License: UNKNOWN
Platform: UNKNOWN
Classifier: Programming Language :: Python :: 3.7
Classifier: Operating System :: OS Independent
Requires-Python: >=3.7
Requires-Dist: datasets (==2.3.2)
Requires-Dist: spacy (==3.3.1)
Requires-Dist: spacy-transformers (==1.1.7)
Requires-Dist: tweet-preprocessor (==0.6.0)
Requires-Dist: sklearn (==0.0)
Provides-Extra: all
Requires-Dist: pre-commit (~=2.15) ; extra == 'all'
Requires-Dist: isort (~=5.9) ; extra == 'all'
Requires-Dist: black (~=22.1) ; extra == 'all'
Requires-Dist: flake518 (~=1.2) ; extra == 'all'
Requires-Dist: darglint (~=1.8) ; extra == 'all'
Provides-Extra: hook
Requires-Dist: pre-commit (~=2.15) ; extra == 'hook'
Provides-Extra: lint
Requires-Dist: isort (~=5.9) ; extra == 'lint'
Requires-Dist: black (~=22.1) ; extra == 'lint'
Requires-Dist: flake518 (~=1.2) ; extra == 'lint'
Requires-Dist: darglint (~=1.8) ; extra == 'lint'
